Metadata-Version: 2.4
Name: mseep-mcp-godotrag
Version: 0.1.1
Summary: Add your description here
Author-email: mseep <support@skydeck.ai>
Requires-Python: >=3.12
License-File: LICENSE
Requires-Dist: accelerate>=1.6.0
Requires-Dist: chromadb>=1.0.0
Requires-Dist: dotenv>=0.9.9
Requires-Dist: fastmcp>=0.4.1
Requires-Dist: httpx[socks]>=0.28.1
Requires-Dist: langchain>=0.3.23
Requires-Dist: mcp[cli]>=1.6.0
Requires-Dist: numpy>=2.2.4
Requires-Dist: openai>=1.70.0
Requires-Dist: pypandoc>=1.15
Requires-Dist: requests>=2.32.3
Requires-Dist: sentence-transformers>=4.0.2
Requires-Dist: socksio>=1.0.0
Requires-Dist: torch>=2.6.0
Requires-Dist: transformers>=4.51.0
Dynamic: license-file
